ohno/__init__.py
ohno/exceptions.py
ohno/logger.py
ohno/logparser.py
ohno/version.py
ohno/client/__init__.py
ohno/client/monitor.py
ohno/client/parse.py
ohno/main/client.py
ohno/main/result.py
ohno/main/executor/__init__.py
ohno/main/executor/base.py
ohno/main/executor/shell.py
ohno/tests/__init__.py
ohno/tests/helpers.sh
ohno/tests/test_client.py
ohno/tests/test_client.sh
ohno/tests/test_utils.py
ohno/utils/__init__.py
ohno/utils/fileio.py
ohno/utils/terminal.py
ohno-0.0.11.dist-info/LICENSE
ohno-0.0.11.dist-info/METADATA
ohno-0.0.11.dist-info/WHEEL
ohno-0.0.11.dist-info/entry_points.txt
ohno-0.0.11.dist-info/top_level.txt
ohno-0.0.11.dist-info/RECORD
