Metadata-Version: 2.1
Name: ohno
Version: 0.0.11
Summary: A command line client, wrapper, and Python module for formatting errors.
Home-page: https://github.com/vsoch/ohno
Author: Vanessa Sochat
Author-email: vsoch@users.noreply.github.com
Maintainer: Vanessa Sochat
License: LICENSE
Keywords: error,capture,submission
Platform: UNKNOWN
Classifier: Intended Audience :: Science/Research
Classifier: Intended Audience :: Developers
Classifier: License :: OSI Approved :: Mozilla Public License 2.0 (MPL 2.0)
Classifier: Programming Language :: C
Classifier: Programming Language :: Python
Classifier: Topic :: Software Development
Classifier: Topic :: Scientific/Engineering
Classifier: Operating System :: Unix
Classifier: Programming Language :: Python :: 3.8
License-File: LICENSE
Provides-Extra: all
Requires-Dist: pytest (>=4.6.2) ; extra == 'all'
Requires-Dist: jinja2 ; extra == 'all'
Requires-Dist: archspec ; extra == 'all'
